acp/__init__.py
acp-0.0.0.dist-info/DESCRIPTION.rst
acp-0.0.0.dist-info/METADATA
acp-0.0.0.dist-info/RECORD
acp-0.0.0.dist-info/WHEEL
acp-0.0.0.dist-info/metadata.json
acp-0.0.0.dist-info/top_level.txt
