Metadata-Version: 2.0
Name: acp
Version: 0.0.0
Summary: anywhere copy'n paste
Home-page: https://github.com/reorx/acp
Author: reorx
Author-email: novoreorx@gmail.com
License: UNKNOWN
Platform: UNKNOWN
Requires-Dist: requests
